[
    {
        "id": "0309e329-3af8-44e6-a666-994e08b816c8",
        "user_id": "5d310dd7-4b9a-49ad-8c33-ed44439d75bb",
        "name": "Finance - Manager",
        "description": "Group for Finance - Manager",
        "data": {
            "config": {
                "share": "members"
            }
        },
        "meta": null,
        "permissions": {
            "workspace": {
                "models": false,
                "knowledge": true,
                "prompts": false,
                "tools": false,
                "skills": false,
                "models_import": false,
                "models_export": false,
                "prompts_import": false,
                "prompts_export": false,
                "tools_import": false,
                "tools_export": false
            },
            "sharing": {
                "models": false,
                "public_models": false,
                "knowledge": false,
                "public_knowledge": false,
                "prompts": false,
                "public_prompts": false,
                "tools": false,
                "public_tools": false,
                "skills": false,
                "public_skills": false,
                "notes": false,
                "public_notes": false,
                "public_chats": false,
                "public_calendars": false
            },
            "access_grants": {
                "allow_users": true
            },
            "chat": {
                "controls": true,
                "valves": true,
                "system_prompt": true,
                "params": true,
                "file_upload": true,
                "web_upload": true,
                "delete": true,
                "delete_message": true,
                "continue_response": true,
                "regenerate_response": true,
                "rate_response": true,
                "edit": true,
                "share": true,
                "export": true,
                "stt": true,
                "tts": true,
                "call": true,
                "multiple_models": true,
                "temporary": true,
                "temporary_enforced": false
            },
            "features": {
                "api_keys": false,
                "notes": true,
                "channels": true,
                "folders": true,
                "direct_tool_servers": false,
                "web_search": true,
                "image_generation": false,
                "code_interpreter": false,
                "memories": true,
                "automations": false,
                "calendar": true
            },
            "settings": {
                "interface": true
            }
        },
        "created_at": 1784303196,
        "updated_at": 1784303196,
        "member_count": 0
    },
    {
        "id": "13b52c81-eff3-47e4-80a8-10c665e37784",
        "user_id": "5d310dd7-4b9a-49ad-8c33-ed44439d75bb",
        "name": "HR - Manager",
        "description": "Group for HR - Manager",
        "data": {
            "config": {
                "share": "members"
            }
        },
        "meta": null,
        "permissions": {
            "workspace": {
                "models": false,
                "knowledge": true,
                "prompts": false,
                "tools": false,
                "skills": false,
                "models_import": false,
                "models_export": false,
                "prompts_import": false,
                "prompts_export": false,
                "tools_import": false,
                "tools_export": false
            },
            "sharing": {
                "models": false,
                "public_models": false,
                "knowledge": false,
                "public_knowledge": false,
                "prompts": false,
                "public_prompts": false,
                "tools": false,
                "public_tools": false,
                "skills": false,
                "public_skills": false,
                "notes": false,
                "public_notes": false,
                "public_chats": false,
                "public_calendars": false
            },
            "access_grants": {
                "allow_users": true
            },
            "chat": {
                "controls": true,
                "valves": true,
                "system_prompt": true,
                "params": true,
                "file_upload": true,
                "web_upload": true,
                "delete": true,
                "delete_message": true,
                "continue_response": true,
                "regenerate_response": true,
                "rate_response": true,
                "edit": true,
                "share": true,
                "export": true,
                "stt": true,
                "tts": true,
                "call": true,
                "multiple_models": true,
                "temporary": true,
                "temporary_enforced": false
            },
            "features": {
                "api_keys": false,
                "notes": true,
                "channels": true,
                "folders": true,
                "direct_tool_servers": false,
                "web_search": true,
                "image_generation": false,
                "code_interpreter": false,
                "memories": true,
                "automations": false,
                "calendar": true
            },
            "settings": {
                "interface": true
            }
        },
        "created_at": 1784303198,
        "updated_at": 1784304425,
        "member_count": 1
    },
    {
        "id": "17e06578-d8e0-4134-81e3-a859c5f158b1",
        "user_id": "5d310dd7-4b9a-49ad-8c33-ed44439d75bb",
        "name": "Admins",
        "description": "",
        "data": {
            "config": {
                "share": "members"
            }
        },
        "meta": null,
        "permissions": {
            "workspace": {
                "models": true,
                "knowledge": true,
                "prompts": true,
                "tools": true,
                "skills": true,
                "models_import": true,
                "models_export": true,
                "prompts_import": true,
                "prompts_export": true,
                "tools_import": true,
                "tools_export": true,
                "skills_import": true,
                "skills_export": true
            },
            "sharing": {
                "models": true,
                "public_models": true,
                "knowledge": true,
                "public_knowledge": true,
                "prompts": true,
                "public_prompts": true,
                "tools": true,
                "public_tools": true,
                "skills": true,
                "public_skills": true,
                "notes": true,
                "public_notes": true,
                "folders": true,
                "public_chats": true,
                "public_calendars": true
            },
            "access_grants": {
                "allow_users": true
            },
            "chat": {
                "controls": true,
                "valves": true,
                "system_prompt": true,
                "params": true,
                "file_upload": true,
                "web_upload": true,
                "delete": true,
                "delete_message": true,
                "continue_response": true,
                "regenerate_response": true,
                "rate_response": true,
                "edit": true,
                "share": true,
                "export": true,
                "import": true,
                "stt": true,
                "tts": true,
                "call": true,
                "multiple_models": true,
                "temporary": true,
                "temporary_enforced": true
            },
            "features": {
                "api_keys": true,
                "notes": true,
                "channels": true,
                "folders": true,
                "direct_tool_servers": true,
                "web_search": true,
                "image_generation": true,
                "code_interpreter": true,
                "memories": true,
                "automations": true,
                "calendar": true,
                "webhooks": true
            },
            "settings": {
                "interface": true
            }
        },
        "created_at": 1783385666,
        "updated_at": 1783385735,
        "member_count": 2
    },
    {
        "id": "414dfc1d-7fe3-48cd-b148-8497bd695b73",
        "user_id": "5d310dd7-4b9a-49ad-8c33-ed44439d75bb",
        "name": "Org - General",
        "description": "Group for Org - General",
        "data": {
            "config": {
                "share": "members"
            }
        },
        "meta": null,
        "permissions": {
            "workspace": {
                "models": false,
                "knowledge": true,
                "prompts": false,
                "tools": false,
                "skills": false,
                "models_import": false,
                "models_export": false,
                "prompts_import": false,
                "prompts_export": false,
                "tools_import": false,
                "tools_export": false
            },
            "sharing": {
                "models": false,
                "public_models": false,
                "knowledge": false,
                "public_knowledge": false,
                "prompts": false,
                "public_prompts": false,
                "tools": false,
                "public_tools": false,
                "skills": false,
                "public_skills": false,
                "notes": false,
                "public_notes": false,
                "public_chats": false,
                "public_calendars": false
            },
            "access_grants": {
                "allow_users": true
            },
            "chat": {
                "controls": true,
                "valves": true,
                "system_prompt": true,
                "params": true,
                "file_upload": true,
                "web_upload": true,
                "delete": true,
                "delete_message": true,
                "continue_response": true,
                "regenerate_response": true,
                "rate_response": true,
                "edit": true,
                "share": true,
                "export": true,
                "stt": true,
                "tts": true,
                "call": true,
                "multiple_models": true,
                "temporary": true,
                "temporary_enforced": false
            },
            "features": {
                "api_keys": false,
                "notes": true,
                "channels": true,
                "folders": true,
                "direct_tool_servers": false,
                "web_search": true,
                "image_generation": false,
                "code_interpreter": false,
                "memories": true,
                "automations": false,
                "calendar": true
            },
            "settings": {
                "interface": true
            }
        },
        "created_at": 1784303181,
        "updated_at": 1784303181,
        "member_count": 0
    },
    {
        "id": "50e407d9-4756-4aeb-9ac9-3f99d275e3b7",
        "user_id": "5d310dd7-4b9a-49ad-8c33-ed44439d75bb",
        "name": "Commerce - Operation",
        "description": "Group for Commerce - Operation",
        "data": {
            "config": {
                "share": "members"
            }
        },
        "meta": null,
        "permissions": {
            "workspace": {
                "models": false,
                "knowledge": true,
                "prompts": false,
                "tools": false,
                "skills": false,
                "models_import": false,
                "models_export": false,
                "prompts_import": false,
                "prompts_export": false,
                "tools_import": false,
                "tools_export": false,
                "skills_import": false,
                "skills_export": false
            },
            "sharing": {
                "models": false,
                "public_models": false,
                "knowledge": false,
                "public_knowledge": false,
                "prompts": false,
                "public_prompts": false,
                "tools": false,
                "public_tools": false,
                "skills": false,
                "public_skills": false,
                "notes": false,
                "public_notes": false,
                "folders": false,
                "public_chats": false,
                "public_calendars": false
            },
            "access_grants": {
                "allow_users": true
            },
            "chat": {
                "controls": true,
                "valves": true,
                "system_prompt": true,
                "params": true,
                "file_upload": true,
                "web_upload": true,
                "delete": true,
                "delete_message": true,
                "continue_response": true,
                "regenerate_response": true,
                "rate_response": true,
                "edit": true,
                "share": true,
                "export": true,
                "import": true,
                "stt": true,
                "tts": true,
                "call": true,
                "multiple_models": true,
                "temporary": true,
                "temporary_enforced": false
            },
            "features": {
                "api_keys": false,
                "notes": true,
                "channels": true,
                "folders": true,
                "direct_tool_servers": false,
                "web_search": true,
                "image_generation": false,
                "code_interpreter": false,
                "memories": true,
                "automations": false,
                "calendar": true,
                "webhooks": false
            },
            "settings": {
                "interface": true
            }
        },
        "created_at": 1784303185,
        "updated_at": 1784876026,
        "member_count": 1
    },
    {
        "id": "768416a7-4602-4471-af88-2aa36e43b5b1",
        "user_id": "5d310dd7-4b9a-49ad-8c33-ed44439d75bb",
        "name": "Erify - Offset",
        "description": "Group for Erify - Offset",
        "data": {
            "config": {
                "share": "members"
            }
        },
        "meta": null,
        "permissions": {
            "workspace": {
                "models": false,
                "knowledge": true,
                "prompts": false,
                "tools": false,
                "skills": false,
                "models_import": false,
                "models_export": false,
                "prompts_import": false,
                "prompts_export": false,
                "tools_import": false,
                "tools_export": false
            },
            "sharing": {
                "models": false,
                "public_models": false,
                "knowledge": false,
                "public_knowledge": false,
                "prompts": false,
                "public_prompts": false,
                "tools": false,
                "public_tools": false,
                "skills": false,
                "public_skills": false,
                "notes": false,
                "public_notes": false,
                "public_chats": false,
                "public_calendars": false
            },
            "access_grants": {
                "allow_users": true
            },
            "chat": {
                "controls": true,
                "valves": true,
                "system_prompt": true,
                "params": true,
                "file_upload": true,
                "web_upload": true,
                "delete": true,
                "delete_message": true,
                "continue_response": true,
                "regenerate_response": true,
                "rate_response": true,
                "edit": true,
                "share": true,
                "export": true,
                "stt": true,
                "tts": true,
                "call": true,
                "multiple_models": true,
                "temporary": true,
                "temporary_enforced": false
            },
            "features": {
                "api_keys": false,
                "notes": true,
                "channels": true,
                "folders": true,
                "direct_tool_servers": false,
                "web_search": true,
                "image_generation": false,
                "code_interpreter": false,
                "memories": true,
                "automations": false,
                "calendar": true
            },
            "settings": {
                "interface": true
            }
        },
        "created_at": 1784303188,
        "updated_at": 1784303188,
        "member_count": 0
    },
    {
        "id": "9c912c64-6bfe-4c0d-a8e5-f416d8e5fe56",
        "user_id": "5d310dd7-4b9a-49ad-8c33-ed44439d75bb",
        "name": "Erify - Onset",
        "description": "Group for Erify - Onset",
        "data": {
            "config": {
                "share": "members"
            }
        },
        "meta": null,
        "permissions": {
            "workspace": {
                "models": false,
                "knowledge": true,
                "prompts": false,
                "tools": false,
                "skills": false,
                "models_import": false,
                "models_export": false,
                "prompts_import": false,
                "prompts_export": false,
                "tools_import": false,
                "tools_export": false
            },
            "sharing": {
                "models": false,
                "public_models": false,
                "knowledge": false,
                "public_knowledge": false,
                "prompts": false,
                "public_prompts": false,
                "tools": false,
                "public_tools": false,
                "skills": false,
                "public_skills": false,
                "notes": false,
                "public_notes": false,
                "public_chats": false,
                "public_calendars": false
            },
            "access_grants": {
                "allow_users": true
            },
            "chat": {
                "controls": true,
                "valves": true,
                "system_prompt": true,
                "params": true,
                "file_upload": true,
                "web_upload": true,
                "delete": true,
                "delete_message": true,
                "continue_response": true,
                "regenerate_response": true,
                "rate_response": true,
                "edit": true,
                "share": true,
                "export": true,
                "stt": true,
                "tts": true,
                "call": true,
                "multiple_models": true,
                "temporary": true,
                "temporary_enforced": false
            },
            "features": {
                "api_keys": false,
                "notes": true,
                "channels": true,
                "folders": true,
                "direct_tool_servers": false,
                "web_search": true,
                "image_generation": false,
                "code_interpreter": false,
                "memories": true,
                "automations": false,
                "calendar": true
            },
            "settings": {
                "interface": true
            }
        },
        "created_at": 1784303191,
        "updated_at": 1784303191,
        "member_count": 0
    },
    {
        "id": "a0c6d928-ed7a-4528-95dd-887a82a97752",
        "user_id": "5d310dd7-4b9a-49ad-8c33-ed44439d75bb",
        "name": "Erisa - Creator",
        "description": "Group for Erisa - Creator",
        "data": {
            "config": {
                "share": "members"
            }
        },
        "meta": null,
        "permissions": {
            "workspace": {
                "models": false,
                "knowledge": true,
                "prompts": false,
                "tools": false,
                "skills": false,
                "models_import": false,
                "models_export": false,
                "prompts_import": false,
                "prompts_export": false,
                "tools_import": false,
                "tools_export": false
            },
            "sharing": {
                "models": false,
                "public_models": false,
                "knowledge": false,
                "public_knowledge": false,
                "prompts": false,
                "public_prompts": false,
                "tools": false,
                "public_tools": false,
                "skills": false,
                "public_skills": false,
                "notes": false,
                "public_notes": false,
                "public_chats": false,
                "public_calendars": false
            },
            "access_grants": {
                "allow_users": true
            },
            "chat": {
                "controls": true,
                "valves": true,
                "system_prompt": true,
                "params": true,
                "file_upload": true,
                "web_upload": true,
                "delete": true,
                "delete_message": true,
                "continue_response": true,
                "regenerate_response": true,
                "rate_response": true,
                "edit": true,
                "share": true,
                "export": true,
                "stt": true,
                "tts": true,
                "call": true,
                "multiple_models": true,
                "temporary": true,
                "temporary_enforced": false
            },
            "features": {
                "api_keys": false,
                "notes": true,
                "channels": true,
                "folders": true,
                "direct_tool_servers": false,
                "web_search": true,
                "image_generation": false,
                "code_interpreter": false,
                "memories": true,
                "automations": false,
                "calendar": true
            },
            "settings": {
                "interface": true
            }
        },
        "created_at": 1784303192,
        "updated_at": 1784874289,
        "member_count": 2
    },
    {
        "id": "a56a6a87-6942-4b4a-a7d0-eb86f9862859",
        "user_id": "5d310dd7-4b9a-49ad-8c33-ed44439d75bb",
        "name": "Erisa - Campaign",
        "description": "Group for Erisa - Campaign",
        "data": {
            "config": {
                "share": "members"
            }
        },
        "meta": null,
        "permissions": {
            "workspace": {
                "models": false,
                "knowledge": true,
                "prompts": false,
                "tools": false,
                "skills": false,
                "models_import": false,
                "models_export": false,
                "prompts_import": false,
                "prompts_export": false,
                "tools_import": false,
                "tools_export": false
            },
            "sharing": {
                "models": false,
                "public_models": false,
                "knowledge": false,
                "public_knowledge": false,
                "prompts": false,
                "public_prompts": false,
                "tools": false,
                "public_tools": false,
                "skills": false,
                "public_skills": false,
                "notes": false,
                "public_notes": false,
                "public_chats": false,
                "public_calendars": false
            },
            "access_grants": {
                "allow_users": true
            },
            "chat": {
                "controls": true,
                "valves": true,
                "system_prompt": true,
                "params": true,
                "file_upload": true,
                "web_upload": true,
                "delete": true,
                "delete_message": true,
                "continue_response": true,
                "regenerate_response": true,
                "rate_response": true,
                "edit": true,
                "share": true,
                "export": true,
                "stt": true,
                "tts": true,
                "call": true,
                "multiple_models": true,
                "temporary": true,
                "temporary_enforced": false
            },
            "features": {
                "api_keys": false,
                "notes": true,
                "channels": true,
                "folders": true,
                "direct_tool_servers": false,
                "web_search": true,
                "image_generation": false,
                "code_interpreter": false,
                "memories": true,
                "automations": false,
                "calendar": true
            },
            "settings": {
                "interface": true
            }
        },
        "created_at": 1784303194,
        "updated_at": 1784303194,
        "member_count": 0
    },
    {
        "id": "ac8a3e5d-76d0-486b-9c9a-576e6c587b1b",
        "user_id": "5d310dd7-4b9a-49ad-8c33-ed44439d75bb",
        "name": "Management team",
        "description": "Group for Management team",
        "data": {
            "config": {
                "share": "members"
            }
        },
        "meta": null,
        "permissions": {
            "workspace": {
                "models": false,
                "knowledge": true,
                "prompts": false,
                "tools": false,
                "skills": false,
                "models_import": false,
                "models_export": false,
                "prompts_import": false,
                "prompts_export": false,
                "tools_import": false,
                "tools_export": false
            },
            "sharing": {
                "models": false,
                "public_models": false,
                "knowledge": false,
                "public_knowledge": false,
                "prompts": false,
                "public_prompts": false,
                "tools": false,
                "public_tools": false,
                "skills": false,
                "public_skills": false,
                "notes": false,
                "public_notes": false,
                "public_chats": false,
                "public_calendars": false
            },
            "access_grants": {
                "allow_users": true
            },
            "chat": {
                "controls": true,
                "valves": true,
                "system_prompt": true,
                "params": true,
                "file_upload": true,
                "web_upload": true,
                "delete": true,
                "delete_message": true,
                "continue_response": true,
                "regenerate_response": true,
                "rate_response": true,
                "edit": true,
                "share": true,
                "export": true,
                "stt": true,
                "tts": true,
                "call": true,
                "multiple_models": true,
                "temporary": true,
                "temporary_enforced": false
            },
            "features": {
                "api_keys": false,
                "notes": true,
                "channels": true,
                "folders": true,
                "direct_tool_servers": false,
                "web_search": true,
                "image_generation": false,
                "code_interpreter": false,
                "memories": true,
                "automations": false,
                "calendar": true
            },
            "settings": {
                "interface": true
            }
        },
        "created_at": 1784303207,
        "updated_at": 1784303207,
        "member_count": 0
    },
    {
        "id": "e5867280-ba3e-4463-bba4-bdae77469876",
        "user_id": "5d310dd7-4b9a-49ad-8c33-ed44439d75bb",
        "name": "Commerce - Sales",
        "description": "Group for Commerce - Sales",
        "data": {
            "config": {
                "share": "members"
            }
        },
        "meta": null,
        "permissions": {
            "workspace": {
                "models": false,
                "knowledge": true,
                "prompts": false,
                "tools": false,
                "skills": false,
                "models_import": false,
                "models_export": false,
                "prompts_import": false,
                "prompts_export": false,
                "tools_import": false,
                "tools_export": false,
                "skills_import": false,
                "skills_export": false
            },
            "sharing": {
                "models": false,
                "public_models": false,
                "knowledge": false,
                "public_knowledge": false,
                "prompts": false,
                "public_prompts": false,
                "tools": false,
                "public_tools": false,
                "skills": false,
                "public_skills": false,
                "notes": false,
                "public_notes": false,
                "folders": false,
                "public_chats": false,
                "public_calendars": false
            },
            "access_grants": {
                "allow_users": true
            },
            "chat": {
                "controls": true,
                "valves": true,
                "system_prompt": true,
                "params": true,
                "file_upload": true,
                "web_upload": true,
                "delete": true,
                "delete_message": true,
                "continue_response": true,
                "regenerate_response": true,
                "rate_response": true,
                "edit": true,
                "share": true,
                "export": true,
                "import": true,
                "stt": true,
                "tts": true,
                "call": true,
                "multiple_models": true,
                "temporary": true,
                "temporary_enforced": false
            },
            "features": {
                "api_keys": false,
                "notes": true,
                "channels": true,
                "folders": true,
                "direct_tool_servers": false,
                "web_search": true,
                "image_generation": false,
                "code_interpreter": false,
                "memories": true,
                "automations": false,
                "calendar": true,
                "webhooks": false
            },
            "settings": {
                "interface": true
            }
        },
        "created_at": 1784303183,
        "updated_at": 1784876041,
        "member_count": 1
    }
]
